pduq/__init__.py
pduq/_version.py
pduq/dbf_calc.py
pduq/invariant_calc.py
pduq/uq_plot.py
pduq/utils.py
pduq/tests/CU-MG_param_gen.tdb
pduq/tests/__init__.py
pduq/tests/conftest.py
pduq/tests/dask_example.py
pduq/tests/test_dbf_invariant.py
pduq/tests/trace.csv
pduq-0.1.0.dist-info/AUTHORS.rst
pduq-0.1.0.dist-info/LICENSE
pduq-0.1.0.dist-info/METADATA
pduq-0.1.0.dist-info/WHEEL
pduq-0.1.0.dist-info/top_level.txt
pduq-0.1.0.dist-info/RECORD
